ninia/__init__.py
ninia/example.py
ninia/mw_species_.py
ninia/object.py
ninia/old_relax.py
ninia/output.py
ninia/relax.py
ninia/sisso.py
ninia/utils.py
ninia/data/mm_of_elements.csv
ninia/input/SISSO.in.jinja2
ninia/input/SISSO_job.sh.jinja2
ninia/input/pbs.sh
ninia/input/relax.i
ninia/input/relax.jinja2
ninia/input/slurm.jinja2
ninia/input/slurm.sh
ninia-0.0.85.dist-info/LICENSE
ninia-0.0.85.dist-info/METADATA
ninia-0.0.85.dist-info/WHEEL
ninia-0.0.85.dist-info/top_level.txt
ninia-0.0.85.dist-info/RECORD
